longprocess/__init__.py
longprocess/longprocess.py
longprocess-0.3.0.dist-info/WHEEL
longprocess-0.3.0.dist-info/METADATA
longprocess-0.3.0.dist-info/RECORD
