Metadata-Version: 2.1
Name: longprocess
Version: 0.3.0
Summary: 
License: MIT
Author: yohan-pg
Author-email: pg.yohan@gmail.com
Requires-Python: >=3.8,<4.0
Classifier: License :: OSI Approved :: MIT License
Classifier: Programming Language :: Python :: 3
Classifier: Programming Language :: Python :: 3.10
Classifier: Programming Language :: Python :: 3.8
Classifier: Programming Language :: Python :: 3.9
